edgembar/AutoEquil.py
edgembar/CenteredCubic.py
edgembar/Cli.py
edgembar/DiscoverEdges.py
edgembar/Edge.py
edgembar/Env.py
edgembar/GlobalOptions.py
edgembar/Graph.py
edgembar/GraphSearch.py
edgembar/HtmlUtils.py
edgembar/ImportEdge.py
edgembar/Names.py
edgembar/OptUtils.py
edgembar/Results.py
edgembar/Splines.py
edgembar/Stage.py
edgembar/TimeSeriesAnalysis.py
edgembar/Trial.py
edgembar/VBA.py
edgembar/__init__.py
edgembar/amber2dats.py
edgembar/scripts.py
edgembar/bin/edgembar
edgembar/bin/edgembar-WriteGraphHtml.py
edgembar/bin/edgembar-amber2dats.py
edgembar/bin/edgembar-calcamberboresch.py
edgembar/bin/edgembar_omp
edgembar/include/nlopt.h
edgembar/include/nlopt.hpp
edgembar/include/openblas/cblas.h
edgembar/include/openblas/f77blas.h
edgembar/include/openblas/lapack.h
edgembar/include/openblas/lapacke.h
edgembar/include/openblas/lapacke_config.h
edgembar/include/openblas/lapacke_example_aux.h
edgembar/include/openblas/lapacke_mangling.h
edgembar/include/openblas/lapacke_utils.h
edgembar/include/openblas/openblas_config.h
edgembar/lib/libnlopt.so
edgembar/lib/libnlopt.so.0
edgembar/lib/libnlopt.so.0.12.0
edgembar/lib/libopenblas.so
edgembar/lib/libopenblas.so.0
edgembar/lib/libopenblas.so.0.3
edgembar/lib/cmake/OpenBLAS/OpenBLASConfig.cmake
edgembar/lib/cmake/OpenBLAS/OpenBLASConfigVersion.cmake
edgembar/lib/cmake/OpenBLAS/OpenBLASTargets-release.cmake
edgembar/lib/cmake/OpenBLAS/OpenBLASTargets.cmake
edgembar/lib/cmake/nlopt/NLoptConfig.cmake
edgembar/lib/cmake/nlopt/NLoptConfigVersion.cmake
edgembar/lib/cmake/nlopt/NLoptLibraryDepends-release.cmake
edgembar/lib/cmake/nlopt/NLoptLibraryDepends.cmake
edgembar/lib/pkgconfig/nlopt.pc
edgembar/lib/pkgconfig/openblas.pc
edgembar/pkgdata/__init__.py
edgembar/pkgdata/edge.css
edgembar/pkgdata/graph.css
edgembar/pkgdata/selerow.js
edgembar/pkgdata/sorttable.js
edgembar/pkgdata/tschart.js
edgembar/pkgdata/vis-iface.js
edgembar/pkgdata/vis-network.min.js
edgembar-3.5.8.dist-info/METADATA
edgembar-3.5.8.dist-info/WHEEL
edgembar-3.5.8.dist-info/entry_points.txt
edgembar-3.5.8.dist-info/RECORD
