Metadata-Version: 2.2
Name: edgembar
Version: 3.5.8
Summary: Companion library to the edgembar C++ program for analyzing free energy molecular dynamics simulations
Keywords: mbar
Author-Email: "Timothy J. Giese" <TimothyJGiese@gmail.com>
Classifier: Programming Language :: Python :: 3
Classifier: Development Status :: 5 - Production/Stable
Requires-Python: >=3.7
Requires-Dist: numpy
Requires-Dist: rdkit
Requires-Dist: matplotlib
Requires-Dist: pyyaml
Requires-Dist: scipy
Requires-Dist: importlib-metadata
